{"marketTypeCode":"01","rdTermCode":"01","containerTypeCode":"01","paymentTermCode":"01","polCode":"CNNGB","podCode":"DEHAM","qtyUnit":"T","baseYearWeek":"202036","interval":"daily","Cell":[{"intervalTimestamp":"20200423","open":811.0,"high":842.0,"low":785.0,"close":842.0,"changeValue":842.0,"changeRate":1.0,"volume":1204},{"intervalTimestamp":"20200508","open":842.0,"high":860.0,"low":742.0,"close":811.0,"changeValue":811.0,"changeRate":1.0,"volume":1414},{"intervalTimestamp":"20200704","open":741.0,"high":835.0,"low":741.0,"close":835.0,"changeValue":835.0,"changeRate":1.0,"volume":258},{"intervalTimestamp":"20200609","open":835.0,"high":835.0,"low":835.0,"close":835.0,"changeValue":835.0,"changeRate":1.0,"volume":10},{"intervalTimestamp":"20200618","open":835.0,"high":835.0,"low":835.0,"close":835.0,"changeValue":835.0,"changeRate":1.0,"volume":10},{"intervalTimestamp":"20200622","open":754.0,"high":754.0,"low":754.0,"close":754.0,"changeValue":754.0,"changeRate":1.0,"volume":2},{"intervalTimestamp":"20200626","open":835.0,"high":835.0,"low":835.0,"close":835.0,"changeValue":835.0,"changeRate":1.0,"volume":20},{"intervalTimestamp":"20200519","open":792.0,"high":810.0,"low":792.0,"close":810.0,"changeValue":810.0,"changeRate":1.0,"volume":18},{"intervalTimestamp":"20200617","open":807.0,"high":807.0,"low":807.0,"close":807.0,"changeValue":807.0,"changeRate":1.0,"volume":300},{"intervalTimestamp":"20200601","open":808.0,"high":808.0,"low":792.0,"close":792.0,"changeValue":792.0,"changeRate":1.0,"volume":541},{"intervalTimestamp":"20200624","open":811.0,"high":811.0,"low":811.0,"close":811.0,"changeValue":811.0,"changeRate":1.0,"volume":1},{"intervalTimestamp":"20200427","open":798.0,"high":800.0,"low":782.0,"close":800.0,"changeValue":800.0,"changeRate":1.0,"volume":900},{"intervalTimestamp":"20200503","open":835.0,"high":845.0,"low":835.0,"close":845.0,"changeValue":845.0,"changeRate":1.0,"volume":140},{"intervalTimestamp":"20200506","open":808.0,"high":810.0,"low":795.0,"close":810.0,"changeValue":810.0,"changeRate":1.0,"volume":222},{"intervalTimestamp":"20200511","open":808.0,"high":810.0,"low":766.0,"close":810.0,"changeValue":810.0,"changeRate":1.0,"volume":19},{"intervalTimestamp":"20200619","open":835.0,"high":835.0,"low":810.0,"close":810.0,"changeValue":810.0,"changeRate":1.0,"volume":3},{"intervalTimestamp":"20200507","open":783.0,"high":783.0,"low":783.0,"close":783.0,"changeValue":783.0,"changeRate":1.0,"volume":300}]}
