{"offerNumber":"F202004230903424707630009429","baseYearWeek":"202040","offerChangeSeq":8,"offerQty":50,"tradeClosing":"20220101010101010000","aggDealQty":12,"aggDealPrice":627.0,"aggDealAmt":7524.0,"aggLeftQty":38,"aggLeftPrice":627.0,"aggLeftAmt":23826.0,"dealLog":[{"eventTimestamp":"20200519165548740520","referenceEventNumber":"D202005191655487386920003528","referenceEventChangeSeq":0,"dealQty":12,"dealPrice":627.0,"dealAmt":7524.0,"offerQty":50,"leftQty":38,"leftPrice":627.0,"leftAmt":23826.0},{"eventTimestamp":"20200519165548818257","referenceEventNumber":"D202005191655487386920003528","referenceEventChangeSeq":0,"dealQty":12,"dealPrice":627.0,"dealAmt":7524.0,"offerQty":50,"leftQty":38,"leftPrice":627.0,"leftAmt":23826.0}]}
