{"offerNumber":"F202005071536066023640009725","baseYearWeek":"202027","offerChangeSeq":1,"offerQty":10,"tradeClosing":"20220101010101010000","aggDealQty":10,"aggDealPrice":801.0,"aggDealAmt":8010.0,"aggLeftQty":0,"aggLeftPrice":801.0,"aggLeftAmt":0.0,"dealLog":[{"eventTimestamp":"20200507153607401128","referenceEventNumber":"D202005071536073961820002882","referenceEventChangeSeq":0,"dealQty":10,"dealPrice":801.0,"dealAmt":8010.0,"offerQty":10,"leftQty":0,"leftPrice":801.0,"leftAmt":0.0},{"eventTimestamp":"20200507153607591672","referenceEventNumber":"D202005071536073961820002882","referenceEventChangeSeq":0,"dealQty":10,"dealPrice":801.0,"dealAmt":8010.0,"offerQty":10,"leftQty":0,"leftPrice":801.0,"leftAmt":0.0}]}
